compie/__init__.py
compute/__init__.py
pycompute/__init__.py
whirlcalc/__init__.py
compie-2.0.1.dist-info/LICENSE
compie-2.0.1.dist-info/METADATA
compie-2.0.1.dist-info/WHEEL
compie-2.0.1.dist-info/top_level.txt
compie-2.0.1.dist-info/RECORD
