Metadata-Version: 2.1
Name: compie
Version: 2.0.1
Summary: A Python module made for use with numbers and data
Home-page: https://github.com/Whirlpool-Programmer/pycompute
Author: Whirlpool-Programmer
Author-email: whirlpool.programmer@outlook.com
License: MIT License
Platform: UNKNOWN
Classifier: Programming Language :: Python :: 2
Classifier: Programming Language :: Python :: 3
Classifier: License :: OSI Approved :: MIT License
Classifier: Operating System :: OS Independent
License-File: LICENSE
